jasonpi/__init__.py
jasonpi/apps.py
jasonpi/auth.py
jasonpi/base.py
jasonpi/models.py
jasonpi/normalizers.py
jasonpi/serializers.py
jasonpi/tests.py
jasonpi/urls.py
jasonpi/utils.py
jasonpi/views.py
jasonpi/migrations/0001_initial.py
jasonpi/migrations/0002_auto_20180124_1514.py
jasonpi/migrations/__init__.py
jasonpi-0.14.0.dist-info/METADATA
jasonpi-0.14.0.dist-info/RECORD
jasonpi-0.14.0.dist-info/WHEEL
jasonpi-0.14.0.dist-info/top_level.txt
jasonpi-0.14.0.dist-info/zip-safe
