Metadata-Version: 2.1
Name: jasonpi
Version: 0.14.0
Summary: Authentication package to use with django-rest-framework & json-api
Home-page: http://github.com/gobadiah/jasonpi
Author: Michaël Journo
Author-email: gobadiah@gmail.com
License: MIT
Platform: UNKNOWN
Requires-Dist: djangorestframework
Requires-Dist: django
Requires-Dist: boto3
Requires-Dist: pyjwt
Requires-Dist: httplib2
Requires-Dist: oauth2client
Requires-Dist: google-api-python-client
Requires-Dist: facebook-sdk
Requires-Dist: inflect
